visionviz/__init__.py
visionviz-0.1.0.dist-info/METADATA
visionviz-0.1.0.dist-info/WHEEL
visionviz-0.1.0.dist-info/licenses/LICENSE
visionviz-0.1.0.dist-info/RECORD
